README.md
setup.py
MF_File/__init__.py
MF_File/app.py
MF_File/config.py
MF_File/statusCode.json
MF_File.egg-info/PKG-INFO
MF_File.egg-info/SOURCES.txt
MF_File.egg-info/dependency_links.txt
MF_File.egg-info/requires.txt
MF_File.egg-info/top_level.txt