Metadata-Version: 1.0
Name: MF-File
Version: 1.0.4
Summary: 蝰蛇软件工作室-文件操作包
Home-page: https://git-codecommit.us-west-2.amazonaws.com/v1/repos/MF_file_python
Author: 林睿霖
Author-email: limitlin@outlook.com
License: UNKNOWN
Platform: UNKNOWN
